README.rst
setup.py
Corsa.egg-info/PKG-INFO
Corsa.egg-info/SOURCES.txt
Corsa.egg-info/dependency_links.txt
Corsa.egg-info/entry_points.txt
Corsa.egg-info/requires.txt
Corsa.egg-info/top_level.txt
corsa/__init__.py
corsa/app.py
corsa/proxy.py
corsa.egg-info/SOURCES.txt