Metadata-Version: 1.0
Name: corsa
Version: 0.1.1
Summary: CORS proxy and web server for static apps
Home-page: https://github.com/olt/corsa
Author: Oliver Tonnhofer
Author-email: olt@bogosoft.com
License: MIT
Platform: UNKNOWN
